fetchgraph/__init__.py
fetchgraph/core/__init__.py
fetchgraph/core/context.py
fetchgraph/core/models.py
fetchgraph/core/protocols.py
fetchgraph/core/utils.py
fetchgraph/parsing/__init__.py
fetchgraph/parsing/exceptions.py
fetchgraph/parsing/extract_json.py
fetchgraph/parsing/json_parser.py
fetchgraph/parsing/plan_parser.py
fetchgraph/prompts/plan_generic.md
fetchgraph/prompts/synth_generic.md
fetchgraph/providers/__init__.py
fetchgraph/relational/__init__.py
fetchgraph/relational/models.py
fetchgraph/relational/schema.py
fetchgraph/relational/types.py
fetchgraph/relational/dsl/__init__.py
fetchgraph/relational/dsl/ast.py
fetchgraph/relational/dsl/compile.py
fetchgraph/relational/dsl/diagnostics.py
fetchgraph/relational/dsl/normalize.py
fetchgraph/relational/dsl/parser.py
fetchgraph/relational/providers/__init__.py
fetchgraph/relational/providers/base.py
fetchgraph/relational/providers/composite_provider.py
fetchgraph/relational/providers/pandas_provider.py
fetchgraph/relational/providers/sql_provider.py
fetchgraph/relational/providers/sql/__init__.py
fetchgraph/relational/providers/sql/builder.py
fetchgraph/relational/providers/sql/dialects.py
fetchgraph/relational/semantic/__init__.py
fetchgraph/relational/semantic/backend.py
fetchgraph/utils/__init__.py
fetchgraph/utils/log_context.py
fetchgraph-0.2.0.dist-info/licenses/LICENSE
fetchgraph-0.2.0.dist-info/METADATA
fetchgraph-0.2.0.dist-info/WHEEL
fetchgraph-0.2.0.dist-info/top_level.txt
fetchgraph-0.2.0.dist-info/RECORD
