Metadata-Version: 2.4
Name: fetchgraph
Version: 0.2.0
Summary: Graph-like planning → context fetching → synthesis agent (library-style).
Author: Alexander Onischenko
License-Expression: MIT
Project-URL: Homepage, https://github.com/AlexanderOnischenko/fetchgraph
Project-URL: Repository, https://github.com/AlexanderOnischenko/fetchgraph
Project-URL: Documentation, https://github.com/AlexanderOnischenko/fetchgraph#readme
Project-URL: Issues, https://github.com/AlexanderOnischenko/fetchgraph/issues
Keywords: agents,context,langgraph,planning,llm
Requires-Python: >=3.11
License-File: LICENSE
Requires-Dist: pydantic>=2.6
Requires-Dist: pandas>=2.0
Provides-Extra: dev
Requires-Dist: pytest>=9.0; extra == "dev"
Requires-Dist: pre-commit; extra == "dev"
Requires-Dist: pydantic-settings>=2.2; extra == "dev"
Requires-Dist: python-dotenv>=1.0; extra == "dev"
Requires-Dist: ruff; extra == "dev"
Requires-Dist: pyright; extra == "dev"
Requires-Dist: build; extra == "dev"
Requires-Dist: twine; extra == "dev"
Provides-Extra: demo
Requires-Dist: pydantic-settings>=2.12; extra == "demo"
Requires-Dist: python-dotenv>=1.0; extra == "demo"
Requires-Dist: openai; extra == "demo"
Dynamic: license-file
